{"API_KEY":"9088f3a19564351cc470a8f1d3f25745","API_SECRET":"9088f3a19564351cc470a8f1d3f25745","userMap":{"Dan`":"daiakuji","KALOKAGATHIA":"guyggi","McNozes":"elitistamusical","Rick971":"rick9791","anaoao":"floyd7375","ann_candy":"anaxxrita","basedg0d":"rootertunes","dank":"vssff","denzel":"gandasommano","gambozino":"fpalindrome","joka":"jokatk","killmaster":"kill_master","leg":"ttsda","mrbonez":"mrbonez1232","ogui":"plan_g","pizzacntg":"soadroxs","pompom":"lovelychienne","putasEVinhoVerde":"armancinho","rick971":"rick9791","sugoiuguu":"sugoiuguu","vim":"sugoiuguu"}}